processVCF/VCF.py
processVCF/__init__.py
processVCF-1.0.4.1.dist-info/LICENSE
processVCF-1.0.4.1.dist-info/METADATA
processVCF-1.0.4.1.dist-info/WHEEL
processVCF-1.0.4.1.dist-info/top_level.txt
processVCF-1.0.4.1.dist-info/RECORD
