Metadata-Version: 2.1
Name: processVCF
Version: 1.0.4.1
Summary: Package to parse VCF files.
Home-page: https://github.com/brownmp/processVCF
Author: Maxwell Brown
Author-email: mbrown@broadinstitute.org
License: MIT License
